{
  "ColorBlack": "#000000",
  "ColorWhite": "#ffffff",
  "ColorGray50": "#f9fafb",
  "ColorGray100": "#f9fafb",
  "ColorGray200": "#e5e7eb",
  "ColorGray300": "#d1d5db",
  "ColorGray400": "#9ca3af",
  "ColorGray500": "#6b7280",
  "ColorGray600": "#4b5563",
  "ColorGray700": "#374151",
  "ColorGray8000": "#1f2937",
  "ColorGray8001": "#000000",
  "ColorGray900": "#111827",
  "ColorRed50": "#fef2f2",
  "ColorRed100": "#fee2e2",
  "ColorRed200": "#fecaca",
  "ColorRed300": "#fca5a5",
  "ColorRed400": "#f87171",
  "ColorRed500": "#ef4444",
  "ColorRed600": "#dc2626",
  "ColorRed700": "#b91c1c",
  "ColorRed800": "#991b1b",
  "ColorYellow50": "#fefce8",
  "ColorYellow100": "#fef9c3",
  "ColorYellow200": "#fef08a",
  "ColorYellow300": "#fde047",
  "ColorYellow400": "#facc15",
  "ColorYellow500": "#eab308",
  "ColorYellow600": "#ca8a04",
  "ColorYellow700": "#a16207",
  "ColorYellow800": "#854d0e",
  "ColorYellow900": "#713f12",
  "ColorGreen50": "#f0fdf4",
  "ColorGreen100": "#dcfce7",
  "ColorGreen200": "#bbf7d0",
  "ColorGreen300": "#86efac",
  "ColorGreen400": "#4ade80",
  "ColorGreen500": "#22c55e",
  "ColorGreen600": "#16a34a",
  "ColorGreen700": "#15803d",
  "ColorGreen800": "#166534",
  "ColorGreen900": "#14532d",
  "ColorBlue50": "#eff6ff",
  "ColorBlue100": "#dbeafe",
  "ColorBlue200": "#bfdbfe",
  "ColorBlue300": "#93c5fd",
  "ColorBlue400": "#60a5fa",
  "ColorBlue500": "#3b82f6",
  "ColorBlue600": "#2563eb",
  "ColorBlue700": "#1d4ed8",
  "ColorBlue800": "#1e40af",
  "ColorBlue900": "#1e3a8a",
  "ColorIndigo50": "#eef2ff",
  "ColorIndigo100": "#e0e7ff",
  "ColorIndigo200": "#c7d2fe",
  "ColorIndigo300": "#a5b4fc",
  "ColorIndigo500": "#818cf8",
  "ColorIndigo600": "#4f46e5",
  "ColorIndigo700": "#4338ca",
  "ColorIndigo800": "#3730a3",
  "ColorIndigo900": "#312e81",
  "ColorPurple50": "#faf5ff",
  "ColorPurple100": "#f3e8ff",
  "ColorPurple200": "#e9d5ff",
  "ColorPurple300": "#d8b4fe",
  "ColorPurple400": "#c084fc",
  "ColorPurple500": "#8b5cf6",
  "ColorPurple600": "#9333ea",
  "ColorPurple700": "#7e22ce",
  "ColorPurple800": "#6b21a8",
  "ColorPurple900": "#581c87",
  "ColorPink50": "#fdf2f8",
  "ColorPink100": "#fce7f3",
  "ColorPink200": "#fbcfe8",
  "ColorPink300": "#f9a8d4",
  "ColorPink400": "#f472b6",
  "ColorPink500": "#ec4899",
  "ColorPink600": "#db2777",
  "ColorPink700": "#be185d",
  "ColorPink800": "#9d174d",
  "ColorPink900": "#831843",
  "FontText6xlRegular": {"fontSize":64,"textDecoration":"none","fontFamily":"Helvetica Neue","fontWeight":400,"fontStyle":"normal","fontStretch":"normal","letterSpacing":0,"lineHeight":96,"paragraphIndent":0,"paragraphSpacing":0,"textCase":"none"},
  "FontText5xlRegular": {"fontSize":48,"textDecoration":"none","fontFamily":"Helvetica Neue","fontWeight":400,"fontStyle":"normal","fontStretch":"normal","letterSpacing":0,"lineHeight":72,"paragraphIndent":0,"paragraphSpacing":0,"textCase":"none"},
  "FontText4xlRegular": {"fontSize":36,"textDecoration":"none","fontFamily":"Helvetica Neue","fontWeight":400,"fontStyle":"normal","fontStretch":"normal","letterSpacing":0,"lineHeight":54,"paragraphIndent":0,"paragraphSpacing":0,"textCase":"none"},
  "FontText3xlRegular": {"fontSize":30,"textDecoration":"none","fontFamily":"Helvetica Neue","fontWeight":400,"fontStyle":"normal","fontStretch":"normal","letterSpacing":0,"lineHeight":45,"paragraphIndent":0,"paragraphSpacing":0,"textCase":"none"},
  "FontText2xlRegular": {"fontSize":24,"textDecoration":"none","fontFamily":"Helvetica Neue","fontWeight":400,"fontStyle":"normal","fontStretch":"normal","letterSpacing":0,"lineHeight":36,"paragraphIndent":0,"paragraphSpacing":0,"textCase":"none"},
  "FontTextXlRegular": {"fontSize":20,"textDecoration":"none","fontFamily":"Helvetica Neue","fontWeight":400,"fontStyle":"normal","fontStretch":"normal","letterSpacing":0,"lineHeight":30,"paragraphIndent":0,"paragraphSpacing":0,"textCase":"none"},
  "FontTextLgRegular": {"fontSize":18,"textDecoration":"none","fontFamily":"Helvetica Neue","fontWeight":400,"fontStyle":"normal","fontStretch":"normal","letterSpacing":0,"lineHeight":27,"paragraphIndent":0,"paragraphSpacing":0,"textCase":"none"},
  "FontTextBaseRegular": {"fontSize":16,"textDecoration":"none","fontFamily":"Helvetica Neue","fontWeight":400,"fontStyle":"normal","fontStretch":"normal","letterSpacing":0,"lineHeight":24,"paragraphIndent":0,"paragraphSpacing":0,"textCase":"none"},
  "FontTextSmRegular": {"fontSize":14,"textDecoration":"none","fontFamily":"Helvetica Neue","fontWeight":400,"fontStyle":"normal","fontStretch":"normal","letterSpacing":0,"lineHeight":21,"paragraphIndent":0,"paragraphSpacing":0,"textCase":"none"},
  "FontTextXsRegular": {"fontSize":12,"textDecoration":"none","fontFamily":"Helvetica Neue","fontWeight":400,"fontStyle":"normal","fontStretch":"normal","letterSpacing":0,"lineHeight":18,"paragraphIndent":0,"paragraphSpacing":0,"textCase":"none"},
  "TypographyText6xlRegularFontSize": 64,
  "TypographyText6xlRegularTextDecoration": "none",
  "TypographyText6xlRegularFontFamily": "Helvetica Neue",
  "TypographyText6xlRegularFontWeight": 400,
  "TypographyText6xlRegularFontStyle": "normal",
  "TypographyText6xlRegularFontStretch": "normal",
  "TypographyText6xlRegularLetterSpacing": 0,
  "TypographyText6xlRegularLineHeight": 96,
  "TypographyText6xlRegularParagraphIndent": 0,
  "TypographyText6xlRegularParagraphSpacing": 0,
  "TypographyText6xlRegularTextCase": "none",
  "TypographyText5xlRegularFontSize": 48,
  "TypographyText5xlRegularTextDecoration": "none",
  "TypographyText5xlRegularFontFamily": "Helvetica Neue",
  "TypographyText5xlRegularFontWeight": 400,
  "TypographyText5xlRegularFontStyle": "normal",
  "TypographyText5xlRegularFontStretch": "normal",
  "TypographyText5xlRegularLetterSpacing": 0,
  "TypographyText5xlRegularLineHeight": 72,
  "TypographyText5xlRegularParagraphIndent": 0,
  "TypographyText5xlRegularParagraphSpacing": 0,
  "TypographyText5xlRegularTextCase": "none",
  "TypographyText4xlRegularFontSize": 36,
  "TypographyText4xlRegularTextDecoration": "none",
  "TypographyText4xlRegularFontFamily": "Helvetica Neue",
  "TypographyText4xlRegularFontWeight": 400,
  "TypographyText4xlRegularFontStyle": "normal",
  "TypographyText4xlRegularFontStretch": "normal",
  "TypographyText4xlRegularLetterSpacing": 0,
  "TypographyText4xlRegularLineHeight": 54,
  "TypographyText4xlRegularParagraphIndent": 0,
  "TypographyText4xlRegularParagraphSpacing": 0,
  "TypographyText4xlRegularTextCase": "none",
  "TypographyText3xlRegularFontSize": 30,
  "TypographyText3xlRegularTextDecoration": "none",
  "TypographyText3xlRegularFontFamily": "Helvetica Neue",
  "TypographyText3xlRegularFontWeight": 400,
  "TypographyText3xlRegularFontStyle": "normal",
  "TypographyText3xlRegularFontStretch": "normal",
  "TypographyText3xlRegularLetterSpacing": 0,
  "TypographyText3xlRegularLineHeight": 45,
  "TypographyText3xlRegularParagraphIndent": 0,
  "TypographyText3xlRegularParagraphSpacing": 0,
  "TypographyText3xlRegularTextCase": "none",
  "TypographyText2xlRegularFontSize": 24,
  "TypographyText2xlRegularTextDecoration": "none",
  "TypographyText2xlRegularFontFamily": "Helvetica Neue",
  "TypographyText2xlRegularFontWeight": 400,
  "TypographyText2xlRegularFontStyle": "normal",
  "TypographyText2xlRegularFontStretch": "normal",
  "TypographyText2xlRegularLetterSpacing": 0,
  "TypographyText2xlRegularLineHeight": 36,
  "TypographyText2xlRegularParagraphIndent": 0,
  "TypographyText2xlRegularParagraphSpacing": 0,
  "TypographyText2xlRegularTextCase": "none",
  "TypographyTextXlRegularFontSize": 20,
  "TypographyTextXlRegularTextDecoration": "none",
  "TypographyTextXlRegularFontFamily": "Helvetica Neue",
  "TypographyTextXlRegularFontWeight": 400,
  "TypographyTextXlRegularFontStyle": "normal",
  "TypographyTextXlRegularFontStretch": "normal",
  "TypographyTextXlRegularLetterSpacing": 0,
  "TypographyTextXlRegularLineHeight": 30,
  "TypographyTextXlRegularParagraphIndent": 0,
  "TypographyTextXlRegularParagraphSpacing": 0,
  "TypographyTextXlRegularTextCase": "none",
  "TypographyTextLgRegularFontSize": 18,
  "TypographyTextLgRegularTextDecoration": "none",
  "TypographyTextLgRegularFontFamily": "Helvetica Neue",
  "TypographyTextLgRegularFontWeight": 400,
  "TypographyTextLgRegularFontStyle": "normal",
  "TypographyTextLgRegularFontStretch": "normal",
  "TypographyTextLgRegularLetterSpacing": 0,
  "TypographyTextLgRegularLineHeight": 27,
  "TypographyTextLgRegularParagraphIndent": 0,
  "TypographyTextLgRegularParagraphSpacing": 0,
  "TypographyTextLgRegularTextCase": "none",
  "TypographyTextBaseRegularFontSize": 16,
  "TypographyTextBaseRegularTextDecoration": "none",
  "TypographyTextBaseRegularFontFamily": "Helvetica Neue",
  "TypographyTextBaseRegularFontWeight": 400,
  "TypographyTextBaseRegularFontStyle": "normal",
  "TypographyTextBaseRegularFontStretch": "normal",
  "TypographyTextBaseRegularLetterSpacing": 0,
  "TypographyTextBaseRegularLineHeight": 24,
  "TypographyTextBaseRegularParagraphIndent": 0,
  "TypographyTextBaseRegularParagraphSpacing": 0,
  "TypographyTextBaseRegularTextCase": "none",
  "TypographyTextSmRegularFontSize": 14,
  "TypographyTextSmRegularTextDecoration": "none",
  "TypographyTextSmRegularFontFamily": "Helvetica Neue",
  "TypographyTextSmRegularFontWeight": 400,
  "TypographyTextSmRegularFontStyle": "normal",
  "TypographyTextSmRegularFontStretch": "normal",
  "TypographyTextSmRegularLetterSpacing": 0,
  "TypographyTextSmRegularLineHeight": 21,
  "TypographyTextSmRegularParagraphIndent": 0,
  "TypographyTextSmRegularParagraphSpacing": 0,
  "TypographyTextSmRegularTextCase": "none",
  "TypographyTextXsRegularFontSize": 12,
  "TypographyTextXsRegularTextDecoration": "none",
  "TypographyTextXsRegularFontFamily": "Helvetica Neue",
  "TypographyTextXsRegularFontWeight": 400,
  "TypographyTextXsRegularFontStyle": "normal",
  "TypographyTextXsRegularFontStretch": "normal",
  "TypographyTextXsRegularLetterSpacing": 0,
  "TypographyTextXsRegularLineHeight": 18,
  "TypographyTextXsRegularParagraphIndent": 0,
  "TypographyTextXsRegularParagraphSpacing": 0,
  "TypographyTextXsRegularTextCase": "none"
}